{
  "device_id": "9000008311",
  "month": "2026-06",
  "days": [
    {
      "date": "2026-06-01",
      "totals": {
        "hours": 24,
        "heavy": 229.7500147951,
        "car": 1054.3191499782,
        "bike": 1162.7165894656002,
        "pedestrian": 33.7327252137,
        "heavy_lft": 134.22844207709997,
        "heavy_rgt": 95.52157271820002,
        "car_lft": 754.2077761588,
        "car_rgt": 300.1113738192,
        "bike_lft": 1029.733494846,
        "bike_rgt": 132.9830946196,
        "pedestrian_lft": 22.9872799555,
        "pedestrian_rgt": 10.7454452582,
        "uptime_avg": 0.4510879629625
      }
    },
    {
      "date": "2026-06-02",
      "totals": {
        "hours": 24,
        "heavy": 189.34603146829997,
        "car": 1325.6443066563002,
        "bike": 1008.3001336677,
        "pedestrian": 34.190927790699995,
        "heavy_lft": 126.38465666050001,
        "heavy_rgt": 62.96137480790001,
        "car_lft": 887.1811155342999,
        "car_rgt": 438.46319112180004,
        "bike_lft": 892.0219883408001,
        "bike_rgt": 116.278145327,
        "pedestrian_lft": 27.6575891829,
        "pedestrian_rgt": 6.533338607799999,
        "uptime_avg": 0.4963078703749999
      }
    },
    {
      "date": "2026-06-03",
      "totals": {
        "hours": 6,
        "heavy": 19.745987607700002,
        "car": 72.409009989,
        "bike": 61.9620855614,
        "pedestrian": 1.3803680982,
        "heavy_lft": 9.2246400175,
        "heavy_rgt": 10.521347590200001,
        "car_lft": 48.56016652,
        "car_rgt": 23.848843469000002,
        "bike_lft": 55.4064893629,
        "bike_rgt": 6.5555961985,
        "pedestrian_lft": 1.3803680982,
        "pedestrian_rgt": 0,
        "uptime_avg": 0.32037037036666666
      }
    }
  ],
  "lastUpdated": "2026-06-03T06:53:48.588Z"
}