{
  "device_id": "9000008322",
  "month": "2026-01",
  "days": [
    {
      "date": "2026-01-01",
      "totals": {
        "hours": 20,
        "heavy": 57.000528566599996,
        "car": 1096.5997142526,
        "bike": 142.7076460956,
        "pedestrian": 17.8386926796,
        "heavy_lft": 30.271629332899998,
        "heavy_rgt": 26.728899233800004,
        "car_lft": 513.6373720142,
        "car_rgt": 582.9623422384,
        "bike_lft": 63.6536786297,
        "bike_rgt": 79.053967466,
        "pedestrian_lft": 7.6558718406,
        "pedestrian_rgt": 10.1828208391,
        "uptime_avg": 0.3195138888900001
      }
    },
    {
      "date": "2026-01-02",
      "totals": {
        "hours": 20,
        "heavy": 72.52771723660001,
        "car": 2257.6028353514,
        "bike": 543.2529710504,
        "pedestrian": 41.919014571700004,
        "heavy_lft": 28.375285483499997,
        "heavy_rgt": 44.152431753100004,
        "car_lft": 992.0747838348,
        "car_rgt": 1265.5280515165,
        "bike_lft": 209.2322184308,
        "bike_rgt": 334.0207526195,
        "pedestrian_lft": 21.6392064541,
        "pedestrian_rgt": 20.2798081175,
        "uptime_avg": 0.28136111111
      }
    },
    {
      "date": "2026-01-03",
      "totals": {
        "hours": 20,
        "heavy": 162.5345302578,
        "car": 1736.6525911209,
        "bike": 277.6349946433,
        "pedestrian": 38.10742885929999,
        "heavy_lft": 91.7855967337,
        "heavy_rgt": 70.7489335241,
        "car_lft": 824.4764324692001,
        "car_rgt": 912.1761586516001,
        "bike_lft": 121.74109337350001,
        "bike_rgt": 155.89390127020002,
        "pedestrian_lft": 13.7127753089,
        "pedestrian_rgt": 24.394653550299996,
        "uptime_avg": 0.31051388888500003
      }
    },
    {
      "date": "2026-01-04",
      "totals": {
        "hours": 20,
        "heavy": 21.6566904785,
        "car": 1628.3606294218,
        "bike": 279.8978181446,
        "pedestrian": 21.757654202999998,
        "heavy_lft": 6.4086502009,
        "heavy_rgt": 15.2480402778,
        "car_lft": 767.6886061746002,
        "car_rgt": 860.6720232472,
        "bike_lft": 121.43137062699999,
        "bike_rgt": 158.46644751760002,
        "pedestrian_lft": 10.183198944099999,
        "pedestrian_rgt": 11.5744552589,
        "uptime_avg": 0.31930555556
      }
    },
    {
      "date": "2026-01-05",
      "totals": {
        "hours": 20,
        "heavy": 218.14107483690003,
        "car": 2591.1056796375,
        "bike": 494.3668324429,
        "pedestrian": 51.129241812500005,
        "heavy_lft": 78.34170821720001,
        "heavy_rgt": 139.7993666195,
        "car_lft": 1140.0774853132,
        "car_rgt": 1451.0281943242,
        "bike_lft": 237.9876615393,
        "bike_rgt": 256.37917090359997,
        "pedestrian_lft": 26.6130254847,
        "pedestrian_rgt": 24.516216327900004,
        "uptime_avg": 0.328277777775
      }
    },
    {
      "date": "2026-01-06",
      "totals": {
        "hours": 20,
        "heavy": 65.1789575789,
        "car": 1593.1242209163001,
        "bike": 266.4655686561,
        "pedestrian": 21.9016383386,
        "heavy_lft": 29.7417865796,
        "heavy_rgt": 35.437170999,
        "car_lft": 738.2676575620999,
        "car_rgt": 854.8565633540001,
        "bike_lft": 124.30654930470001,
        "bike_rgt": 142.1590193515,
        "pedestrian_lft": 6.6565609851000005,
        "pedestrian_rgt": 15.245077353699998,
        "uptime_avg": 0.30734722222499994
      }
    },
    {
      "date": "2026-01-07",
      "totals": {
        "hours": 20,
        "heavy": 294.8315331488,
        "car": 3030.08254025,
        "bike": 663.8748673613999,
        "pedestrian": 42.2865384041,
        "heavy_lft": 147.6470834932,
        "heavy_rgt": 147.1844496558,
        "car_lft": 1458.3055177943002,
        "car_rgt": 1571.7770224556,
        "bike_lft": 291.8412453332,
        "bike_rgt": 372.0336220281,
        "pedestrian_lft": 26.8440769987,
        "pedestrian_rgt": 15.442461405400001,
        "uptime_avg": 0.311194444445
      }
    },
    {
      "date": "2026-01-08",
      "totals": {
        "hours": 20,
        "heavy": 189.2970360656,
        "car": 3185.3272384331,
        "bike": 887.9756057482001,
        "pedestrian": 88.39372394419999,
        "heavy_lft": 71.5337646066,
        "heavy_rgt": 117.76327145930001,
        "car_lft": 1532.5298887855,
        "car_rgt": 1652.7973496476002,
        "bike_lft": 360.38494643430005,
        "bike_rgt": 527.5906593138001,
        "pedestrian_lft": 39.7316923944,
        "pedestrian_rgt": 48.662031549800005,
        "uptime_avg": 0.2883055555549999
      }
    },
    {
      "date": "2026-01-09",
      "totals": {
        "hours": 20,
        "heavy": 337.7998012241,
        "car": 3360.7004295680003,
        "bike": 759.448408524,
        "pedestrian": 49.5512152712,
        "heavy_lft": 184.4816158677,
        "heavy_rgt": 153.31818535649998,
        "car_lft": 1516.9803239287,
        "car_rgt": 1843.7201056392003,
        "bike_lft": 298.02362316999995,
        "bike_rgt": 461.42478535399994,
        "pedestrian_lft": 15.9724600425,
        "pedestrian_rgt": 33.5787552288,
        "uptime_avg": 0.23948611111
      }
    },
    {
      "date": "2026-01-10",
      "totals": {
        "hours": 20,
        "heavy": 100.6120925142,
        "car": 2396.3158385475,
        "bike": 439.9521380649,
        "pedestrian": 39.2346161392,
        "heavy_lft": 42.6548713794,
        "heavy_rgt": 57.95722113480001,
        "car_lft": 1169.660165415,
        "car_rgt": 1226.6556731323,
        "bike_lft": 214.2533041453,
        "bike_rgt": 225.69883391989998,
        "pedestrian_lft": 16.5766688062,
        "pedestrian_rgt": 22.657947333,
        "uptime_avg": 0.22554166667
      }
    },
    {
      "date": "2026-01-11",
      "totals": {
        "hours": 20,
        "heavy": 85.5665906568,
        "car": 1631.384947916,
        "bike": 345.5701315421,
        "pedestrian": 32.540805403,
        "heavy_lft": 50.5278129159,
        "heavy_rgt": 35.0387777408,
        "car_lft": 790.5749880527001,
        "car_rgt": 840.8099598635,
        "bike_lft": 177.2221093471,
        "bike_rgt": 168.348022195,
        "pedestrian_lft": 21.8339606962,
        "pedestrian_rgt": 10.7068447067,
        "uptime_avg": 0.25204166666999994
      }
    },
    {
      "date": "2026-01-12",
      "totals": {
        "hours": 24,
        "heavy": 293.13305087259994,
        "car": 3519.8538627795997,
        "bike": 835.8590288960002,
        "pedestrian": 70.896711034,
        "heavy_lft": 130.5832863661,
        "heavy_rgt": 162.54976450659998,
        "car_lft": 1610.0374220784001,
        "car_rgt": 1909.8164407013999,
        "bike_lft": 263.56965069,
        "bike_rgt": 572.2893782059,
        "pedestrian_lft": 35.565573335299995,
        "pedestrian_rgt": 35.3311376983,
        "uptime_avg": 0.21226851852083337
      }
    },
    {
      "date": "2026-01-13",
      "totals": {
        "hours": 24,
        "heavy": 373.18100266600004,
        "car": 3212.6021108235,
        "bike": 1024.316085873,
        "pedestrian": 104.9900186024,
        "heavy_lft": 189.4596205592,
        "heavy_rgt": 183.72138210670002,
        "car_lft": 1484.4718283269,
        "car_rgt": 1728.1302824964002,
        "bike_lft": 445.8875557355,
        "bike_rgt": 578.4285301374999,
        "pedestrian_lft": 68.53091519760001,
        "pedestrian_rgt": 36.459103404800004,
        "uptime_avg": 0.20444444445
      }
    },
    {
      "date": "2026-01-14",
      "totals": {
        "hours": 3,
        "heavy": 0,
        "car": 0,
        "bike": 0,
        "pedestrian": 0,
        "heavy_lft": 0,
        "heavy_rgt": 0,
        "car_lft": 0,
        "car_rgt": 0,
        "bike_lft": 0,
        "bike_rgt": 0,
        "pedestrian_lft": 0,
        "pedestrian_rgt": 0,
        "uptime_avg": 0
      }
    }
  ],
  "lastUpdated": "2026-01-14T03:48:43.705Z"
}