{
  "device_id": "9000008322",
  "month": "2026-04",
  "days": [
    {
      "date": "2026-04-01",
      "totals": {
        "hours": 19,
        "heavy": 358.7562184077,
        "car": 4195.1664776306,
        "bike": 1627.4105294465,
        "pedestrian": 129.9521706681,
        "heavy_lft": 156.76009850679998,
        "heavy_rgt": 201.99611990119996,
        "car_lft": 2023.8901322835,
        "car_rgt": 2171.2763453471002,
        "bike_lft": 699.0446630772001,
        "bike_rgt": 928.3658663696002,
        "pedestrian_lft": 50.8487809254,
        "pedestrian_rgt": 79.10338974279999,
        "uptime_avg": 0.5153070175473684
      }
    },
    {
      "date": "2026-04-02",
      "totals": {
        "hours": 19,
        "heavy": 371.1555558861999,
        "car": 3660.7083068448,
        "bike": 1869.0142210879999,
        "pedestrian": 71.61357570300001,
        "heavy_lft": 165.103569081,
        "heavy_rgt": 206.05198680529998,
        "car_lft": 1960.9557020411996,
        "car_rgt": 1699.7526048037998,
        "bike_lft": 825.1977946031,
        "bike_rgt": 1043.8164264845,
        "pedestrian_lft": 16.6056405163,
        "pedestrian_rgt": 55.0079351868,
        "uptime_avg": 0.4863157894736842
      }
    },
    {
      "date": "2026-04-03",
      "totals": {
        "hours": 19,
        "heavy": 464.7079148043,
        "car": 2471.8422317095997,
        "bike": 756.0585740093001,
        "pedestrian": 89.70368816,
        "heavy_lft": 397.04284691020007,
        "heavy_rgt": 67.6650678941,
        "car_lft": 1180.1526399263,
        "car_rgt": 1291.689591783,
        "bike_lft": 268.01615843839994,
        "bike_rgt": 488.0424155712001,
        "pedestrian_lft": 34.9924575605,
        "pedestrian_rgt": 54.711230599500006,
        "uptime_avg": 0.46111111111052633
      }
    },
    {
      "date": "2026-04-04",
      "totals": {
        "hours": 19,
        "heavy": 144.9791944127,
        "car": 3130.4152410627003,
        "bike": 738.9399932085998,
        "pedestrian": 67.5340946222,
        "heavy_lft": 58.9213658763,
        "heavy_rgt": 86.05782853670001,
        "car_lft": 1460.0140477855002,
        "car_rgt": 1670.4011932772999,
        "bike_lft": 312.6063564921,
        "bike_rgt": 426.3336367164,
        "pedestrian_lft": 33.0625825797,
        "pedestrian_rgt": 34.471512042200004,
        "uptime_avg": 0.5156286549736843
      }
    },
    {
      "date": "2026-04-05",
      "totals": {
        "hours": 19,
        "heavy": 97.92418954059998,
        "car": 2037.5605997392001,
        "bike": 571.1934360703001,
        "pedestrian": 25.4806758342,
        "heavy_lft": 64.0395371506,
        "heavy_rgt": 33.8846523901,
        "car_lft": 915.3706545017,
        "car_rgt": 1122.1899452373002,
        "bike_lft": 260.9875718359,
        "bike_rgt": 310.2058642344,
        "pedestrian_lft": 8.9146240458,
        "pedestrian_rgt": 16.5660517884,
        "uptime_avg": 0.4804970760263158
      }
    },
    {
      "date": "2026-04-06",
      "totals": {
        "hours": 19,
        "heavy": 76.1784469589,
        "car": 2030.4700917803998,
        "bike": 799.4199678428,
        "pedestrian": 51.6723988437,
        "heavy_lft": 39.150091880000005,
        "heavy_rgt": 37.028355078800004,
        "car_lft": 866.8522519678,
        "car_rgt": 1163.6178398122,
        "bike_lft": 344.60412955629994,
        "bike_rgt": 454.8158382865001,
        "pedestrian_lft": 13.9645251268,
        "pedestrian_rgt": 37.707873717,
        "uptime_avg": 0.48767543859473683
      }
    },
    {
      "date": "2026-04-07",
      "totals": {
        "hours": 19,
        "heavy": 417.7177165877,
        "car": 3120.7281088372,
        "bike": 1881.583389844,
        "pedestrian": 72.5592322943,
        "heavy_lft": 196.2320474254,
        "heavy_rgt": 221.4856691622,
        "car_lft": 1491.9030319969,
        "car_rgt": 1628.8250768400999,
        "bike_lft": 867.2808270352,
        "bike_rgt": 1014.3025628086,
        "pedestrian_lft": 42.5801849168,
        "pedestrian_rgt": 29.9790473774,
        "uptime_avg": 0.5077923976631579
      }
    },
    {
      "date": "2026-04-08",
      "totals": {
        "hours": 19,
        "heavy": 393.7259414963999,
        "car": 3209.5898892036003,
        "bike": 1931.2058083463999,
        "pedestrian": 81.23008098630001,
        "heavy_lft": 183.65632384900002,
        "heavy_rgt": 210.06961764740004,
        "car_lft": 1591.7102280509998,
        "car_rgt": 1617.8796611528999,
        "bike_lft": 886.2819485357999,
        "bike_rgt": 1044.9238598105,
        "pedestrian_lft": 51.13391576950001,
        "pedestrian_rgt": 30.0961652167,
        "uptime_avg": 0.4879093567263158
      }
    },
    {
      "date": "2026-04-09",
      "totals": {
        "hours": 19,
        "heavy": 302.22894153440006,
        "car": 3599.8853134400997,
        "bike": 1791.8702041268998,
        "pedestrian": 100.72292910569999,
        "heavy_lft": 110.51577010710001,
        "heavy_rgt": 191.71317142720005,
        "car_lft": 1586.9957183902002,
        "car_rgt": 2012.8895950497003,
        "bike_lft": 697.1983994022,
        "bike_rgt": 1094.6718047244,
        "pedestrian_lft": 52.136583309,
        "pedestrian_rgt": 48.5863457967,
        "uptime_avg": 0.49187134503684216
      }
    },
    {
      "date": "2026-04-10",
      "totals": {
        "hours": 18,
        "heavy": 348.9073506472,
        "car": 4529.6340383309,
        "bike": 1504.2539242475,
        "pedestrian": 100.98682931009999,
        "heavy_lft": 137.93340553579998,
        "heavy_rgt": 210.97394511149997,
        "car_lft": 2057.0899450776,
        "car_rgt": 2472.5440932534,
        "bike_lft": 708.9192715128,
        "bike_rgt": 795.3346527347999,
        "pedestrian_lft": 55.574071263499995,
        "pedestrian_rgt": 45.4127580465,
        "uptime_avg": 0.5071141975222223
      }
    },
    {
      "date": "2026-04-11",
      "totals": {
        "hours": 19,
        "heavy": 205.1248956277,
        "car": 2615.2897432768,
        "bike": 1140.7503815458,
        "pedestrian": 34.6303119981,
        "heavy_lft": 112.6595062016,
        "heavy_rgt": 92.465389426,
        "car_lft": 1247.2446453317002,
        "car_rgt": 1368.0450979451,
        "bike_lft": 473.5836936993,
        "bike_rgt": 667.1666878468,
        "pedestrian_lft": 18.0565624245,
        "pedestrian_rgt": 16.5737495736,
        "uptime_avg": 0.4859064327421053
      }
    },
    {
      "date": "2026-04-12",
      "totals": {
        "hours": 19,
        "heavy": 102.68877900940001,
        "car": 2893.7937683761,
        "bike": 936.1523240401,
        "pedestrian": 56.9899330267,
        "heavy_lft": 53.078779364599995,
        "heavy_rgt": 49.6099996447,
        "car_lft": 1465.1260108458,
        "car_rgt": 1428.6677575302,
        "bike_lft": 449.55395820179996,
        "bike_rgt": 486.5983658382,
        "pedestrian_lft": 19.0322834097,
        "pedestrian_rgt": 37.9576496169,
        "uptime_avg": 0.5279532163789473
      }
    },
    {
      "date": "2026-04-13",
      "totals": {
        "hours": 19,
        "heavy": 328.47452056419996,
        "car": 4509.390250747299,
        "bike": 1454.6944534150998,
        "pedestrian": 126.32548080320001,
        "heavy_lft": 138.9289971316,
        "heavy_rgt": 189.54552343260002,
        "car_lft": 2114.5915789122,
        "car_rgt": 2394.7986718354005,
        "bike_lft": 616.3347045579001,
        "bike_rgt": 838.3597488575001,
        "pedestrian_lft": 80.90561210809999,
        "pedestrian_rgt": 45.4198686952,
        "uptime_avg": 0.4927485380105263
      }
    },
    {
      "date": "2026-04-14",
      "totals": {
        "hours": 19,
        "heavy": 389.66364988769993,
        "car": 5156.087568663701,
        "bike": 2047.7725069598998,
        "pedestrian": 147.5609243941,
        "heavy_lft": 185.2889634245,
        "heavy_rgt": 204.37468646329998,
        "car_lft": 2521.8228774719,
        "car_rgt": 2634.2646911918,
        "bike_lft": 898.0762774149999,
        "bike_rgt": 1149.6962295450999,
        "pedestrian_lft": 70.8700403977,
        "pedestrian_rgt": 76.6908839964,
        "uptime_avg": 0.4986842105210526
      }
    },
    {
      "date": "2026-04-15",
      "totals": {
        "hours": 19,
        "heavy": 406.0564313533,
        "car": 3728.6829467641005,
        "bike": 2201.6382027810996,
        "pedestrian": 133.2492183956,
        "heavy_lft": 242.63773770850003,
        "heavy_rgt": 163.4186936447,
        "car_lft": 1858.5396278158998,
        "car_rgt": 1870.1433189482,
        "bike_lft": 992.3993484753998,
        "bike_rgt": 1209.2388543059,
        "pedestrian_lft": 72.1569919333,
        "pedestrian_rgt": 61.0922264624,
        "uptime_avg": 0.48368421052631577
      }
    },
    {
      "date": "2026-04-16",
      "totals": {
        "hours": 19,
        "heavy": 514.3544243965,
        "car": 4297.501948110301,
        "bike": 1892.4217337472,
        "pedestrian": 74.9285101032,
        "heavy_lft": 301.4448792499,
        "heavy_rgt": 212.9095451464,
        "car_lft": 1992.6689485322001,
        "car_rgt": 2304.8329995780996,
        "bike_lft": 754.5782340465,
        "bike_rgt": 1137.8434997006,
        "pedestrian_lft": 44.0349497098,
        "pedestrian_rgt": 30.893560393599998,
        "uptime_avg": 0.5037134502894737
      }
    },
    {
      "date": "2026-04-17",
      "totals": {
        "hours": 18,
        "heavy": 318.82127153820005,
        "car": 3345.8882870293996,
        "bike": 1797.8026148386,
        "pedestrian": 108.21335264240001,
        "heavy_lft": 151.4690374553,
        "heavy_rgt": 167.35223408279998,
        "car_lft": 1559.1180655449998,
        "car_rgt": 1786.7702214843998,
        "bike_lft": 693.2468776284999,
        "bike_rgt": 1104.5557372103,
        "pedestrian_lft": 59.962036417700006,
        "pedestrian_rgt": 48.2513162248,
        "uptime_avg": 0.4960030864277778
      }
    },
    {
      "date": "2026-04-18",
      "totals": {
        "hours": 19,
        "heavy": 314.7337316953,
        "car": 3040.7649245371003,
        "bike": 1599.2619041730998,
        "pedestrian": 112.68056378349999,
        "heavy_lft": 171.13824162840004,
        "heavy_rgt": 143.5954900672,
        "car_lft": 1492.8034396453997,
        "car_rgt": 1547.9614848917001,
        "bike_lft": 742.0050188393001,
        "bike_rgt": 857.256885334,
        "pedestrian_lft": 45.18959205290001,
        "pedestrian_rgt": 67.49097173060001,
        "uptime_avg": 0.47875730994210536
      }
    },
    {
      "date": "2026-04-19",
      "totals": {
        "hours": 19,
        "heavy": 165.13810805670002,
        "car": 2294.0669969507,
        "bike": 694.9370464773001,
        "pedestrian": 45.372614410599994,
        "heavy_lft": 105.3943003448,
        "heavy_rgt": 59.7438077117,
        "car_lft": 991.2005453302,
        "car_rgt": 1302.8664516204,
        "bike_lft": 289.89370749930004,
        "bike_rgt": 405.04333897809994,
        "pedestrian_lft": 20.307306275200002,
        "pedestrian_rgt": 25.0653081355,
        "uptime_avg": 0.5386111111157895
      }
    },
    {
      "date": "2026-04-20",
      "totals": {
        "hours": 19,
        "heavy": 472.58834413489996,
        "car": 3519.6645157556995,
        "bike": 1889.2863747424003,
        "pedestrian": 90.07297639180001,
        "heavy_lft": 259.7838670844,
        "heavy_rgt": 212.8044770503,
        "car_lft": 1676.2930630485,
        "car_rgt": 1843.3714527073,
        "bike_lft": 832.2002259512001,
        "bike_rgt": 1057.0861487912,
        "pedestrian_lft": 44.5800060994,
        "pedestrian_rgt": 45.49297029219999,
        "uptime_avg": 0.5146783625842106
      }
    },
    {
      "date": "2026-04-21",
      "totals": {
        "hours": 24,
        "heavy": 450.3384392011,
        "car": 4881.391205519801,
        "bike": 2300.8796189610002,
        "pedestrian": 168.131670993,
        "heavy_lft": 200.7557046109,
        "heavy_rgt": 249.58273459020006,
        "car_lft": 2476.4074559477003,
        "car_rgt": 2404.9837495721,
        "bike_lft": 1065.8558224322,
        "bike_rgt": 1235.0237965284002,
        "pedestrian_lft": 88.3938438349,
        "pedestrian_rgt": 79.73782715830001,
        "uptime_avg": 0.44634259260000003
      }
    },
    {
      "date": "2026-04-22",
      "totals": {
        "hours": 24,
        "heavy": 419.9503831186,
        "car": 3519.9545266099994,
        "bike": 2266.4539506213,
        "pedestrian": 86.99040303950001,
        "heavy_lft": 196.9389571301,
        "heavy_rgt": 223.0114259887,
        "car_lft": 1721.1559143101001,
        "car_rgt": 1798.7986123000003,
        "bike_lft": 1037.5281688451,
        "bike_rgt": 1228.9257817760001,
        "pedestrian_lft": 44.000989510000004,
        "pedestrian_rgt": 42.9894135296,
        "uptime_avg": 0.41692129629583335
      }
    },
    {
      "date": "2026-04-23",
      "totals": {
        "hours": 4,
        "heavy": 0,
        "car": 0,
        "bike": 0,
        "pedestrian": 0,
        "heavy_lft": 0,
        "heavy_rgt": 0,
        "car_lft": 0,
        "car_rgt": 0,
        "bike_lft": 0,
        "bike_rgt": 0,
        "pedestrian_lft": 0,
        "pedestrian_rgt": 0,
        "uptime_avg": 0
      }
    }
  ],
  "lastUpdated": "2026-04-23T04:51:02.940Z"
}